uridx/__init__.py
uridx/config.py
uridx/cli/__init__.py
uridx/cli/main.py
uridx/cli/extract/__init__.py
uridx/cli/extract/base.py
uridx/cli/extract/claude_code.py
uridx/cli/extract/docling.py
uridx/cli/extract/image.py
uridx/cli/extract/markdown.py
uridx/cli/extract/pdf.py
uridx/db/__init__.py
uridx/db/engine.py
uridx/db/models.py
uridx/db/operations.py
uridx/embeddings/__init__.py
uridx/embeddings/ollama.py
uridx/mcp/__init__.py
uridx/mcp/oauth.py
uridx/mcp/server.py
uridx/search/__init__.py
uridx/search/hybrid.py
uridx-0.1.2.dist-info/METADATA
uridx-0.1.2.dist-info/WHEEL
uridx-0.1.2.dist-info/entry_points.txt
uridx-0.1.2.dist-info/licenses/LICENSE
uridx-0.1.2.dist-info/RECORD
