Metadata-Version: 2.4
Name: uridx
Version: 0.1.2
Summary: uridx - Personal Reference Index
Author: Justyn Shull
License-File: LICENSE
Requires-Python: >=3.12
Requires-Dist: fastmcp<3,>=2.0
Requires-Dist: httpx>=0.27
Requires-Dist: rich>=13
Requires-Dist: sqlite-vec>=0.1.6
Requires-Dist: sqlmodel>=0.0.16
Requires-Dist: typer>=0.12
Provides-Extra: dev
Requires-Dist: ruff; extra == 'dev'
Provides-Extra: docling
Requires-Dist: docling>=2.66; extra == 'docling'
Provides-Extra: pdf
Requires-Dist: pdfplumber>=0.10; extra == 'pdf'
